time_series_analyzer/__init__.py
time_series_analyzer/api.py
time_series_analyzer/cli.py
time_series_analyzer/formatters.py
time_series_analyzer/models.py
time_series_analyzer/parsers.py
time_series_analyzer/transfer_function.py
time_series_model_transfer_function_analyzer-0.1.2.dist-info/METADATA
time_series_model_transfer_function_analyzer-0.1.2.dist-info/WHEEL
time_series_model_transfer_function_analyzer-0.1.2.dist-info/entry_points.txt
time_series_model_transfer_function_analyzer-0.1.2.dist-info/licenses/LICENSE
time_series_model_transfer_function_analyzer-0.1.2.dist-info/RECORD
