Metadata-Version: 2.4
Name: time-series-model-transfer-function-analyzer
Version: 0.1.2
Summary: 时序模型传递函数分析器 - 自动推导ARIMA模型的传递函数表达式
Project-URL: Homepage, https://github.com/zym9863/time-series-model-transfer-function-analyzer
Project-URL: Repository, https://github.com/zym9863/time-series-model-transfer-function-analyzer
Project-URL: Issues, https://github.com/zym9863/time-series-model-transfer-function-analyzer/issues
Author-email: zym <ym214413520@gmail.com>
License-File: LICENSE
Keywords: arima,econometrics,signal-processing,time-series,transfer-function
Classifier: Development Status :: 3 - Alpha
Classifier: Intended Audience :: Science/Research
Classifier: License :: OSI Approved :: MIT License
Classifier: Programming Language :: Python :: 3
Classifier: Programming Language :: Python :: 3.9
Classifier: Programming Language :: Python :: 3.10
Classifier: Programming Language :: Python :: 3.11
Classifier: Programming Language :: Python :: 3.12
Classifier: Topic :: Scientific/Engineering :: Information Analysis
Classifier: Topic :: Scientific/Engineering :: Mathematics
Requires-Python: >=3.9
Requires-Dist: click>=8.0
Requires-Dist: fastapi>=0.115.14
Requires-Dist: numpy>=1.24
Requires-Dist: pydantic-settings>=2.10.1
Requires-Dist: pydantic>=2.0
Requires-Dist: python-multipart>=0.0.20
Requires-Dist: pyyaml>=6.0
Requires-Dist: rich>=13.0
Requires-Dist: sympy>=1.12
Requires-Dist: uvicorn[standard]>=0.35.0
Provides-Extra: dev
Requires-Dist: black>=23.0; extra == 'dev'
Requires-Dist: flake8>=6.0; extra == 'dev'
Requires-Dist: isort>=5.12; extra == 'dev'
Requires-Dist: mypy>=1.0; extra == 'dev'
Requires-Dist: pytest-cov>=4.0; extra == 'dev'
Requires-Dist: pytest>=7.0; extra == 'dev'
Provides-Extra: docs
Requires-Dist: myst-parser>=2.0; extra == 'docs'
Requires-Dist: sphinx-rtd-theme>=1.3; extra == 'docs'
Requires-Dist: sphinx>=7.0; extra == 'docs'
